varscope/__init__.py
varscope-0.1.1.dist-info/LICENSE.md
varscope-0.1.1.dist-info/METADATA
varscope-0.1.1.dist-info/WHEEL
varscope-0.1.1.dist-info/RECORD
