Metadata-Version: 2.1
Name: varscope
Version: 0.1.1
Summary: Ultra simple module for creating local scopes in Python
Home-page: https://github.com/jeertmans/varscope
License: MIT
Keywords: scope,python
Author: Jérome Eertmans
Author-email: jeertmans@icloud.com
Requires-Python: >=3.8,<4.0
Classifier: License :: OSI Approved :: MIT License
Classifier: Operating System :: OS Independent
Classifier: Programming Language :: Python :: 3
Classifier: Programming Language :: Python :: 3.8
Classifier: Programming Language :: Python :: 3.9
Classifier: Programming Language :: Python :: 3.10
Classifier: Programming Language :: Python :: 3.11
Classifier: Topic :: Utilities
Project-URL: Documentation, https://eertmans.be/varscope
Project-URL: Repository, https://github.com/jeertmans/varscope
